logseq_compiler/__main__.py
logseq_compiler/block.py
logseq_compiler/compiler.py
logseq_compiler/hugoblock.py
logseq_compiler/link_finder.py
logseq_compiler-0.1.3.dist-info/METADATA
logseq_compiler-0.1.3.dist-info/WHEEL
logseq_compiler-0.1.3.dist-info/RECORD
